Workbook

Sheet README
A1: Clip Live — Financieel model per business model
B2: Versie 1.0 · 2026-05-26 · Voor Sjuul Smits · Vergelijkt 5 SaaS-monetisatiemodellen voor Clip Live
B4: Wat zit hierin
B5: Dit Excel-bestand vergelijkt vijf manieren waarop je Clip Live kunt verdienen. Voor elk model staat een aparte sheet met dezelfde
B6: structuur: gebruikersfunnel (Free → Paid), maandelijkse MRR, churn, cumulatieve omzet over 24 maanden, en LTV / CAC / payback.
B7: De Vergelijking-sheet zet de uitkomsten naast elkaar zodat je in één oogopslag ziet welk model in welke fase het meest oplevert.
B9: Hoe lees je de sheets
B10: • BLAUWE getallen = inputs die jij mag wijzigen (signups, churn, conversie, prijzen, …)
B11: • GELE achtergrond = key assumptions — verandert deze cel en alles in het model herrekent
B12: • ZWARTE getallen = formules — niet aanpassen tenzij je weet wat je doet
B13: • GROENE getallen = links naar andere sheets
B15: Hoe gebruik je dit
B16: 1. Open de Assumpties-sheet en pas de globale getallen aan (DJ-doelgroepgrootte, organische groei, churn).
... B36: Lees ook het bijgeleverde plan-document (CLIP-LIVE-BUSINESS-MODEL-PLAN.docx) — daar staat de strategische context.

Sheet Assumpties
A1: Globale assumpties — pas deze cellen aan voor je eigen scenario
B2: Blauwe / gele cellen zijn aanpasbaar. Alle Model-tabbladen verwijzen hiernaar.
A4: Acquisitie & funnel
B5: Parameter | C5: Waarde | D5: Eenheid | E5: Toelichting / bron
B6: DJ-doelgroep wereldwijd (TAM, bereikbaar via socials) | C6: 100000 | D6: DJs | E6: Conservatief: Europese semi-pro + pro DJs + producers op TikTok/IG/YT
B7: Maandelijkse nieuwe Free signups (maand 1) | C7: 30 | D7: users | E7: Conservatief startaantal — organisch + Sjuul's netwerk
B8: Maandelijkse groei van signups (compounding) | C8: 0.08 | D8: %/mnd | E8: 8% MoM = 2,5x in jaar 1, 6x in jaar 2. Pas aan o.b.v. werkelijke groei
B9: Activeringsratio (Free signup → ≥1 set verwerkt) | C9: 0.55 | D9: % | E9: 55% standaard voor creator tools; <40% = onboarding probleem
B10: Free → betaald conversieratio (organisch) | C10: 0.04 | D10: % | E10: 4% is mediaan voor niche-SaaS (Growth Unhinged 2026)
B11: Aandeel betaalde users dat Pro kiest | C11: 0.85 | D11: % | E11: Pro is veruit het toegankelijkste tier
B12: Aandeel betaalde users dat Studio kiest | C12: 0.1 | D12: % | E12: Studio = labels/venues
B13: Aandeel betaalde users dat Pro+ kiest (Model D only) | C13: 0.3 | D13: % | E13: Wordt herverdeeld vanuit Pro in Model D
A15: Churn (maandelijks, op betaalde tiers)
B16: Parameter | C16: Waarde | D16: Eenheid | E16: Toelichting / bron
B17: Pro churn (maandelijks) | C17: 0.1 | D17: %/mnd | E17: 10%/mnd = 90-dagen LT. Goed voor SMB-SaaS
B18: Studio churn (maandelijks) | C18: 0.05 | D18: %/mnd | E18: Studio = stickier, hogere commitment
B19: Pro+ churn (Model D) | C19: 0.08 | D19: %/mnd | E19: Tussen Pro en Studio in
B20: Credit-pack repeat-purchase | C20: 0.4 | D20: %/mnd | E20: Welk % van credit-kopers koopt opnieuw die maand (Model B+C)
A22: Pricing per tier (EUR per maand, excl. BTW)
B23: Tier / item | C23: Waarde | D23: Eenheid | E23: Toelichting
B24: Pro abonnement | C24: 21.99 | D24: EUR/mnd | E24: Huidige prijs (Stripe Test mode)
B25: Studio abonnement | C25: 200 | D25: EUR/mnd | E25: Huidige prijs (Stripe Test mode)
B26: Pro+ abonnement (Model D) | C26: 49 | D26: EUR/mnd | E26: Voorgestelde mid-tier
B27: Credit-pack (10 extra clips) | C27: 9.99 | D27: EUR/pack | E27: Voor Model B + C
B28: Outcome-fee per virale clip | C28: 2.5 | D28: EUR/clip | E28: Model E — clip >10k views
B29: Basis-fee Outcome model | C29: 4.99 | D29: EUR/mnd | E29: Model E — basis-abonnement
A31: Kosten & marges
B32: Post | C32: Waarde | D32: Eenheid | E32: Toelichting
B33: Stripe transactiekosten | C33: 0.029 | D33: % + €0,25 | E33: Standaard EU
B34: Stripe vaste fee per transactie | C34: 0.25 | D34: EUR | E34: Per geslaagde betaling
B35: Supabase + Cloudflare (vast) | C35: 25 | D35: EUR/mnd | E35: Geldt tot ~50k users
B36: Customer support per Pro-user | C36: 0.5 | D36: EUR/mnd | E36: E-mail / tickets
B37: Customer support per Studio | C37: 5 | D37: EUR/mnd | E37: Hogere SLA-verwachting
B38: CAC organisch (per nieuwe paid) | C38: 8 | D38: EUR/conversion | E38: Tijd-equivalent Sjuul
B39: CAC paid ads (alt scenario) | C39: 35 | D39: EUR/conversion | E39: Indicatie als je ads gaat draaien

Sheet Model A — Current Tiers
A1: Model A — Current Tiers (Free / Pro €21,99 / Studio €200)
B2: Alle blauwe cellen op de Assumpties-sheet sturen dit model aan. MRR-rij = recurring; CumRev = totaal sinds maand 1.
B4: Maand → | C4: M1 | D4: M2 | E4: M3 | F4: M4 | G4: M5 | H4: M6 | I4: M7 | J4: M8 | K4: M9 | L4: M10 | M4: M11 | N4: M12 | O4: M13 | P4: M14 | Q4: M15 | R4: M16 | S4: M17 | T4: M18 | U4: M19 | V4: M20 | W4: M21 | X4: M22 | Y4: M23 | Z4: M24
A5: Acquisitie funnel
B6: Nieuwe Free signups (per maand) | C6: =Assumpties!$C$7 -> 30 | D6: =ROUND(C6*(1+Assumpties!$C$8),0) -> 32 | E6: =ROUND(D6*(1+Assumpties!$C$8),0) -> 35 | F6: =ROUND(E6*(1+Assumpties!$C$8),0) -> 38 | G6: =ROUND(F6*(1+Assumpties!$C$8),0) -> 41 | H6: =ROUND(G6*(1+Assumpties!$C$8),0) -> 44 | I6: =ROUND(H6*(1+Assumpties!$C$8),0) -> 48 | J6: =ROUND(I6*(1+Assumpties!$C$8),0) -> 52 | K6: =ROUND(J6*(1+Assumpties!$C$8),0) -> 56 | ... Z6: =ROUND(Y6*(1+Assumpties!$C$8),0) -> 177
B7: Cumulatieve Free signups | C7: =C6 -> 30 | D7: =C7+D6 -> 62 | E7: =D7+E6 -> 97 | F7: =E7+F6 -> 135 | G7: =F7+G6 -> 176 | H7: =G7+H6 -> 220 | I7: =H7+I6 -> 268 | J7: =I7+J6 -> 320 | K7: =J7+K6 -> 376 | ... Z7: =Y7+Z6 -> 2016
B8: Actieve Free users (na activatie) | C8: =ROUND(C7*Assumpties!$C$9,0) -> 17 | D8: =ROUND(D7*Assumpties!$C$9,0) -> 34 | E8: =ROUND(E7*Assumpties!$C$9,0) -> 53 | F8: =ROUND(F7*Assumpties!$C$9,0) -> 74 | G8: =ROUND(G7*Assumpties!$C$9,0) -> 97 | H8: =ROUND(H7*Assumpties!$C$9,0) -> 121 | I8: =ROUND(I7*Assumpties!$C$9,0) -> 147 | J8: =ROUND(J7*Assumpties!$C$9,0) -> 176 | ... Z8: =ROUND(Z7*Assumpties!$C$9,0) -> 1109
B9: Nieuwe paid conversions (per maand) | C9: =ROUND(C6*Assumpties!$C$9*Assumpties!$C$10,0) -> 1 | D9: =ROUND(D6*Assumpties!$C$9*Assumpties!$C$10,0) -> 1 | E9: =ROUND(E6*Assumpties!$C$9*Assumpties!$C$10,0) -> 1 | F9: =ROUND(F6*Assumpties!$C$9*Assumpties!$C$10,0) -> 1 | G9: =ROUND(G6*Assumpties!$C$9*Assumpties!$C$10,0) -> 1 | H9: =ROUND(H6*Assumpties!$C$9*Assumpties!$C$10,0) -> 1 | I9: =ROUND(I6*Assumpties!$C$9*Assumpties!$C$10,0) -> 1 | J9: =ROUND(J6*Assumpties!$C$9*Assumpties!$C$10,0) -> 1 | ... Z9: =ROUND(Z6*Assumpties!$C$9*Assumpties!$C$10,0) -> 4
A11: Tier-mix: Pro 85% / Studio 10% / Free-only 5%
B12: Nieuwe Pro klanten (per maand) | C12: =ROUND(C9*Assumpties!$C$11,0) -> 1 | D12: =ROUND(D9*Assumpties!$C$11,0) -> 1 | E12: =ROUND(E9*Assumpties!$C$11,0) -> 1 | F12: =ROUND(F9*Assumpties!$C$11,0) -> 1 | G12: =ROUND(G9*Assumpties!$C$11,0) -> 1 | H12: =ROUND(H9*Assumpties!$C$11,0) -> 1 | I12: =ROUND(I9*Assumpties!$C$11,0) -> 1 | J12: =ROUND(J9*Assumpties!$C$11,0) -> 1 | ... Z12: =ROUND(Z9*Assumpties!$C$11,0) -> 3
B13: Actieve Pro klanten | C13: =C12 -> 1 | D13: =ROUND(C13*(1-Assumpties!$C$17)+D12,0) -> 2 | E13: =ROUND(D13*(1-Assumpties!$C$17)+E12,0) -> 3 | F13: =ROUND(E13*(1-Assumpties!$C$17)+F12,0) -> 4 | G13: =ROUND(F13*(1-Assumpties!$C$17)+G12,0) -> 5 | H13: =ROUND(G13*(1-Assumpties!$C$17)+H12,0) -> 6 | I13: =ROUND(H13*(1-Assumpties!$C$17)+I12,0) -> 6 | J13: =ROUND(I13*(1-Assumpties!$C$17)+J12,0) -> 6 | K13: =ROUND(J13*(1-Assumpties!$C$17)+K12,0) -> 6 | ... Z13: =ROUND(Y13*(1-Assumpties!$C$17)+Z12,0) -> 21
B14: Nieuwe Studio klanten (per maand) | C14: =ROUND(C9*Assumpties!$C$12,0) -> 0 | D14: =ROUND(D9*Assumpties!$C$12,0) -> 0 | E14: =ROUND(E9*Assumpties!$C$12,0) -> 0 | F14: =ROUND(F9*Assumpties!$C$12,0) -> 0 | G14: =ROUND(G9*Assumpties!$C$12,0) -> 0 | H14: =ROUND(H9*Assumpties!$C$12,0) -> 0 | I14: =ROUND(I9*Assumpties!$C$12,0) -> 0 | J14: =ROUND(J9*Assumpties!$C$12,0) -> 0 | ... Z14: =ROUND(Z9*Assumpties!$C$12,0) -> 0
B15: Actieve Studio klanten | C15: =C14 -> 0 | D15: =ROUND(C15*(1-Assumpties!$C$18)+D14,0) -> 0 | E15: =ROUND(D15*(1-Assumpties!$C$18)+E14,0) -> 0 | F15: =ROUND(E15*(1-Assumpties!$C$18)+F14,0) -> 0 | G15: =ROUND(F15*(1-Assumpties!$C$18)+G14,0) -> 0 | H15: =ROUND(G15*(1-Assumpties!$C$18)+H14,0) -> 0 | I15: =ROUND(H15*(1-Assumpties!$C$18)+I14,0) -> 0 | J15: =ROUND(I15*(1-Assumpties!$C$18)+J14,0) -> 0 | K15: =ROUND(J15*(1-Assumpties!$C$18)+K14,0) -> 0 | ... Z15: =ROUND(Y15*(1-Assumpties!$C$18)+Z14,0) -> 0
A17: Omzet per maand (EUR)
B18: Pro MRR | C18: =C13*Assumpties!$C$24 -> 21.99 | D18: =D13*Assumpties!$C$24 -> 43.98 | E18: =E13*Assumpties!$C$24 -> 65.97 | F18: =F13*Assumpties!$C$24 -> 87.96 | G18: =G13*Assumpties!$C$24 -> 109.95 | H18: =H13*Assumpties!$C$24 -> 131.94 | I18: =I13*Assumpties!$C$24 -> 131.94 | J18: =J13*Assumpties!$C$24 -> 131.94 | ... Z18: =Z13*Assumpties!$C$24 -> 461.79
B19: Studio MRR | C19: =C15*Assumpties!$C$25 -> 0 | D19: =D15*Assumpties!$C$25 -> 0 | E19: =E15*Assumpties!$C$25 -> 0 | F19: =F15*Assumpties!$C$25 -> 0 | G19: =G15*Assumpties!$C$25 -> 0 | H19: =H15*Assumpties!$C$25 -> 0 | I19: =I15*Assumpties!$C$25 -> 0 | J19: =J15*Assumpties!$C$25 -> 0 | ... Z19: =Z15*Assumpties!$C$25 -> 0
B20: Totaal MRR | C20: =C18+C19 -> 21.99 | D20: =D18+D19 -> 43.98 | E20: =E18+E19 -> 65.97 | F20: =F18+F19 -> 87.96 | G20: =G18+G19 -> 109.95 | H20: =H18+H19 -> 131.94 | I20: =I18+I19 -> 131.94 | J20: =J18+J19 -> 131.94 | ... Z20: =Z18+Z19 -> 461.79
B21: Cumulatieve omzet | C21: =C20 -> 21.99 | D21: =C21+D20 -> 65.97 | E21: =D21+E20 -> 131.94 | F21: =E21+F20 -> 219.9 | G21: =F21+G20 -> 329.85 | H21: =G21+H20 -> 461.79 | I21: =H21+I20 -> 593.73 | J21: =I21+J20 -> 725.67 | K21: =J21+K20 -> 857.61 | ... Z21: =Y21+Z20 -> 5079.69
A23: Kosten & netto winst (EUR)
B24: Stripe fees | C24: =C20*Assumpties!$C$33+(C13+C15)*Assumpties!$C$34 -> 0.88771 | D24: =D20*Assumpties!$C$33+(D13+D15)*Assumpties!$C$34 -> 1.77542 | E24: =E20*Assumpties!$C$33+(E13+E15)*Assumpties!$C$34 -> 2.66313 | F24: =F20*Assumpties!$C$33+(F13+F15)*Assumpties!$C$34 -> 3.55084 | G24: =G20*Assumpties!$C$33+(G13+G15)*Assumpties!$C$34 -> 4.43855 | H24: =H20*Assumpties!$C$33+(H13+H15)*Assumpties!$C$34 -> 5.32626 | I24: =I20*Assumpties!$C$33+(I13+I15)*Assumpties!$C$34 -> 5.32626 | J24: =J20*Assumpties!$C$33+(J13+J15)*Assumpties!$C$34 -> 5.32626 | ... Z24: =Z20*Assumpties!$C$33+(Z13+Z15)*Assumpties!$C$34 -> 18.64191
B25: Support kosten | C25: =C13*Assumpties!$C$36+C15*Assumpties!$C$37 -> 0.5 | D25: =D13*Assumpties!$C$36+D15*Assumpties!$C$37 -> 1 | E25: =E13*Assumpties!$C$36+E15*Assumpties!$C$37 -> 1.5 | F25: =F13*Assumpties!$C$36+F15*Assumpties!$C$37 -> 2 | G25: =G13*Assumpties!$C$36+G15*Assumpties!$C$37 -> 2.5 | H25: =H13*Assumpties!$C$36+H15*Assumpties!$C$37 -> 3 | I25: =I13*Assumpties!$C$36+I15*Assumpties!$C$37 -> 3 | J25: =J13*Assumpties!$C$36+J15*Assumpties!$C$37 -> 3 | ... Z25: =Z13*Assumpties!$C$36+Z15*Assumpties!$C$37 -> 10.5
B26: Vaste platformkosten | C26: =Assumpties!$C$35 -> 25 | D26: =Assumpties!$C$35 -> 25 | E26: =Assumpties!$C$35 -> 25 | F26: =Assumpties!$C$35 -> 25 | G26: =Assumpties!$C$35 -> 25 | H26: =Assumpties!$C$35 -> 25 | I26: =Assumpties!$C$35 -> 25 | J26: =Assumpties!$C$35 -> 25 | ... Z26: =Assumpties!$C$35 -> 25
B27: CAC (organic) — alleen nieuwe paid | C27: =C9*Assumpties!$C$38 -> 8 | D27: =D9*Assumpties!$C$38 -> 8 | E27: =E9*Assumpties!$C$38 -> 8 | F27: =F9*Assumpties!$C$38 -> 8 | G27: =G9*Assumpties!$C$38 -> 8 | H27: =H9*Assumpties!$C$38 -> 8 | I27: =I9*Assumpties!$C$38 -> 8 | J27: =J9*Assumpties!$C$38 -> 8 | ... Z27: =Z9*Assumpties!$C$38 -> 32
B28: Netto winst per maand | C28: =C20-C24-C25-C26-C27 -> -12.39771 | D28: =D20-D24-D25-D26-D27 -> 8.20458 | E28: =E20-E24-E25-E26-E27 -> 28.80687 | F28: =F20-F24-F25-F26-F27 -> 49.40916 | G28: =G20-G24-G25-G26-G27 -> 70.01145 | H28: =H20-H24-H25-H26-H27 -> 90.61374 | I28: =I20-I24-I25-I26-I27 -> 90.61374 | J28: =J20-J24-J25-J26-J27 -> 90.61374 | ... Z28: =Z20-Z24-Z25-Z26-Z27 -> 375.64809
B29: Cumulatieve winst | C29: =C28 -> -12.39771 | D29: =C29+D28 -> -4.19313 | E29: =D29+E28 -> 24.61374 | F29: =E29+F28 -> 74.0229 | G29: =F29+G28 -> 144.03435 | H29: =G29+H28 -> 234.64809 | I29: =H29+I28 -> 325.26183 | J29: =I29+J28 -> 415.87557 | K29: =J29+K28 -> 506.48931 | ... Z29: =Y29+Z28 -> 3799.129
A31: Unit economics
B32: ARPU (M24, EUR/mnd) | Z32: =Z20/MAX(1,Z13+Z15) -> 21.99
B33: Gem. LT Pro (mnd) | Z33: =1/Assumpties!$C$17 -> 10
B34: LTV Pro (EUR) | Z34: =Assumpties!$C$24/Assumpties!$C$17*(1-Assumpties!$C$33) -> 213.5229
B35: LTV Studio (EUR) | Z35: =Assumpties!$C$25/Assumpties!$C$18*(1-Assumpties!$C$33) -> 3884
B36: LTV / CAC (Pro) | Z36: =(Assumpties!$C$24/Assumpties!$C$17*(1-Assumpties!$C$33))/Assumpties!$C$38 -> 26.690362
B37: Payback Pro (mnd) | Z37: =Assumpties!$C$38/Assumpties!$C$24 -> 0.36380173

Sheet Model B — Hybride
A1: Model B — Hybride (Sub + Credit-pack upsell)
B2: Alle blauwe cellen op de Assumpties-sheet sturen dit model aan. MRR-rij = recurring; CumRev = totaal sinds maand 1.
B4: Maand → | C4: M1 | D4: M2 | E4: M3 | F4: M4 | G4: M5 | H4: M6 | I4: M7 | J4: M8 | K4: M9 | L4: M10 | M4: M11 | N4: M12 | O4: M13 | P4: M14 | Q4: M15 | R4: M16 | S4: M17 | T4: M18 | U4: M19 | V4: M20 | W4: M21 | X4: M22 | Y4: M23 | Z4: M24
A5: Acquisitie funnel
B6: Nieuwe Free signups (per maand) | C6: =Assumpties!$C$7 -> 30 | D6: =ROUND(C6*(1+Assumpties!$C$8),0) -> 32 | E6: =ROUND(D6*(1+Assumpties!$C$8),0) -> 35 | F6: =ROUND(E6*(1+Assumpties!$C$8),0) -> 38 | G6: =ROUND(F6*(1+Assumpties!$C$8),0) -> 41 | H6: =ROUND(G6*(1+Assumpties!$C$8),0) -> 44 | I6: =ROUND(H6*(1+Assumpties!$C$8),0) -> 48 | J6: =ROUND(I6*(1+Assumpties!$C$8),0) -> 52 | K6: =ROUND(J6*(1+Assumpties!$C$8),0) -> 56 | ... Z6: =ROUND(Y6*(1+Assumpties!$C$8),0) -> 177
B7: Cumulatieve Free signups | C7: =C6 -> 30 | D7: =C7+D6 -> 62 | E7: =D7+E6 -> 97 | F7: =E7+F6 -> 135 | G7: =F7+G6 -> 176 | H7: =G7+H6 -> 220 | I7: =H7+I6 -> 268 | J7: =I7+J6 -> 320 | K7: =J7+K6 -> 376 | ... Z7: =Y7+Z6 -> 2016
B8: Actieve Free users (na activatie) | C8: =ROUND(C7*Assumpties!$C$9,0) -> 17 | D8: =ROUND(D7*Assumpties!$C$9,0) -> 34 | E8: =ROUND(E7*Assumpties!$C$9,0) -> 53 | F8: =ROUND(F7*Assumpties!$C$9,0) -> 74 | G8: =ROUND(G7*Assumpties!$C$9,0) -> 97 | H8: =ROUND(H7*Assumpties!$C$9,0) -> 121 | I8: =ROUND(I7*Assumpties!$C$9,0) -> 147 | J8: =ROUND(J7*Assumpties!$C$9,0) -> 176 | ... Z8: =ROUND(Z7*Assumpties!$C$9,0) -> 1109
B9: Nieuwe paid conversions (per maand) | C9: =ROUND(C6*Assumpties!$C$9*Assumpties!$C$10,0) -> 1 | D9: =ROUND(D6*Assumpties!$C$9*Assumpties!$C$10,0) -> 1 | E9: =ROUND(E6*Assumpties!$C$9*Assumpties!$C$10,0) -> 1 | F9: =ROUND(F6*Assumpties!$C$9*Assumpties!$C$10,0) -> 1 | G9: =ROUND(G6*Assumpties!$C$9*Assumpties!$C$10,0) -> 1 | H9: =ROUND(H6*Assumpties!$C$9*Assumpties!$C$10,0) -> 1 | I9: =ROUND(I6*Assumpties!$C$9*Assumpties!$C$10,0) -> 1 | J9: =ROUND(J6*Assumpties!$C$9*Assumpties!$C$10,0) -> 1 | ... Z9: =ROUND(Z6*Assumpties!$C$9*Assumpties!$C$10,0) -> 4
A11: Tier-mix idem A + credit-pack upsell op Pro-users
B12: Nieuwe Pro klanten | C12: =ROUND(C9*Assumpties!$C$11,0) -> 1 | D12: =ROUND(D9*Assumpties!$C$11,0) -> 1 | E12: =ROUND(E9*Assumpties!$C$11,0) -> 1 | F12: =ROUND(F9*Assumpties!$C$11,0) -> 1 | G12: =ROUND(G9*Assumpties!$C$11,0) -> 1 | H12: =ROUND(H9*Assumpties!$C$11,0) -> 1 | I12: =ROUND(I9*Assumpties!$C$11,0) -> 1 | J12: =ROUND(J9*Assumpties!$C$11,0) -> 1 | ... Z12: =ROUND(Z9*Assumpties!$C$11,0) -> 3
B13: Actieve Pro klanten | C13: =C12 -> 1 | D13: =ROUND(C13*(1-Assumpties!$C$17)+D12,0) -> 2 | E13: =ROUND(D13*(1-Assumpties!$C$17)+E12,0) -> 3 | F13: =ROUND(E13*(1-Assumpties!$C$17)+F12,0) -> 4 | G13: =ROUND(F13*(1-Assumpties!$C$17)+G12,0) -> 5 | H13: =ROUND(G13*(1-Assumpties!$C$17)+H12,0) -> 6 | I13: =ROUND(H13*(1-Assumpties!$C$17)+I12,0) -> 6 | J13: =ROUND(I13*(1-Assumpties!$C$17)+J12,0) -> 6 | K13: =ROUND(J13*(1-Assumpties!$C$17)+K12,0) -> 6 | ... Z13: =ROUND(Y13*(1-Assumpties!$C$17)+Z12,0) -> 21
B14: Nieuwe Studio klanten | C14: =ROUND(C9*Assumpties!$C$12,0) -> 0 | D14: =ROUND(D9*Assumpties!$C$12,0) -> 0 | E14: =ROUND(E9*Assumpties!$C$12,0) -> 0 | F14: =ROUND(F9*Assumpties!$C$12,0) -> 0 | G14: =ROUND(G9*Assumpties!$C$12,0) -> 0 | H14: =ROUND(H9*Assumpties!$C$12,0) -> 0 | I14: =ROUND(I9*Assumpties!$C$12,0) -> 0 | J14: =ROUND(J9*Assumpties!$C$12,0) -> 0 | ... Z14: =ROUND(Z9*Assumpties!$C$12,0) -> 0
B15: Actieve Studio klanten | C15: =C14 -> 0 | D15: =ROUND(C15*(1-Assumpties!$C$18)+D14,0) -> 0 | E15: =ROUND(D15*(1-Assumpties!$C$18)+E14,0) -> 0 | F15: =ROUND(E15*(1-Assumpties!$C$18)+F14,0) -> 0 | G15: =ROUND(F15*(1-Assumpties!$C$18)+G14,0) -> 0 | H15: =ROUND(G15*(1-Assumpties!$C$18)+H14,0) -> 0 | I15: =ROUND(H15*(1-Assumpties!$C$18)+I14,0) -> 0 | J15: =ROUND(I15*(1-Assumpties!$C$18)+J14,0) -> 0 | K15: =ROUND(J15*(1-Assumpties!$C$18)+K14,0) -> 0 | ... Z15: =ROUND(Y15*(1-Assumpties!$C$18)+Z14,0) -> 0
A17: Credit-pack upsell (€9,99 = 10 extra clips)
B18: Credit-pack kopers per maand (40% van Pro) | C18: =ROUND(C13*Assumpties!$C$20,0) -> 0 | D18: =ROUND(D13*Assumpties!$C$20,0) -> 1 | E18: =ROUND(E13*Assumpties!$C$20,0) -> 1 | F18: =ROUND(F13*Assumpties!$C$20,0) -> 2 | G18: =ROUND(G13*Assumpties!$C$20,0) -> 2 | H18: =ROUND(H13*Assumpties!$C$20,0) -> 2 | I18: =ROUND(I13*Assumpties!$C$20,0) -> 2 | J18: =ROUND(J13*Assumpties!$C$20,0) -> 2 | ... Z18: =ROUND(Z13*Assumpties!$C$20,0) -> 8
A20: Omzet per maand (EUR)
B21: Pro MRR | C21: =C13*Assumpties!$C$24 -> 21.99 | D21: =D13*Assumpties!$C$24 -> 43.98 | E21: =E13*Assumpties!$C$24 -> 65.97 | F21: =F13*Assumpties!$C$24 -> 87.96 | G21: =G13*Assumpties!$C$24 -> 109.95 | H21: =H13*Assumpties!$C$24 -> 131.94 | I21: =I13*Assumpties!$C$24 -> 131.94 | J21: =J13*Assumpties!$C$24 -> 131.94 | ... Z21: =Z13*Assumpties!$C$24 -> 461.79
B22: Studio MRR | C22: =C15*Assumpties!$C$25 -> 0 | D22: =D15*Assumpties!$C$25 -> 0 | E22: =E15*Assumpties!$C$25 -> 0 | F22: =F15*Assumpties!$C$25 -> 0 | G22: =G15*Assumpties!$C$25 -> 0 | H22: =H15*Assumpties!$C$25 -> 0 | I22: =I15*Assumpties!$C$25 -> 0 | J22: =J15*Assumpties!$C$25 -> 0 | ... Z22: =Z15*Assumpties!$C$25 -> 0
B23: Credit-pack omzet | C23: =C18*Assumpties!$C$27 -> 0 | D23: =D18*Assumpties!$C$27 -> 9.99 | E23: =E18*Assumpties!$C$27 -> 9.99 | F23: =F18*Assumpties!$C$27 -> 19.98 | G23: =G18*Assumpties!$C$27 -> 19.98 | H23: =H18*Assumpties!$C$27 -> 19.98 | I23: =I18*Assumpties!$C$27 -> 19.98 | J23: =J18*Assumpties!$C$27 -> 19.98 | ... Z23: =Z18*Assumpties!$C$27 -> 79.92
B24: Totaal omzet (MRR + packs) | C24: =C21+C22+C23 -> 21.99 | D24: =D21+D22+D23 -> 53.97 | E24: =E21+E22+E23 -> 75.96 | F24: =F21+F22+F23 -> 107.94 | G24: =G21+G22+G23 -> 129.93 | H24: =H21+H22+H23 -> 151.92 | I24: =I21+I22+I23 -> 151.92 | J24: =J21+J22+J23 -> 151.92 | ... Z24: =Z21+Z22+Z23 -> 541.71
B25: Cumulatieve omzet | C25: =C24 -> 21.99 | D25: =C25+D24 -> 75.96 | E25: =D25+E24 -> 151.92 | F25: =E25+F24 -> 259.86 | G25: =F25+G24 -> 389.79 | H25: =G25+H24 -> 541.71 | I25: =H25+I24 -> 693.63 | J25: =I25+J24 -> 845.55 | K25: =J25+K24 -> 997.47 | ... Z25: =Y25+Z24 -> 5978.79
A27: Netto winst
B28: Stripe fees | C28: =C24*Assumpties!$C$33+(C13+C15+C18)*Assumpties!$C$34 -> 0.88771 | D28: =D24*Assumpties!$C$33+(D13+D15+D18)*Assumpties!$C$34 -> 2.31513 | E28: =E24*Assumpties!$C$33+(E13+E15+E18)*Assumpties!$C$34 -> 3.20284 | F28: =F24*Assumpties!$C$33+(F13+F15+F18)*Assumpties!$C$34 -> 4.63026 | G28: =G24*Assumpties!$C$33+(G13+G15+G18)*Assumpties!$C$34 -> 5.51797 | H28: =H24*Assumpties!$C$33+(H13+H15+H18)*Assumpties!$C$34 -> 6.40568 | I28: =I24*Assumpties!$C$33+(I13+I15+I18)*Assumpties!$C$34 -> 6.40568 | J28: =J24*Assumpties!$C$33+(J13+J15+J18)*Assumpties!$C$34 -> 6.40568 | ... Z28: =Z24*Assumpties!$C$33+(Z13+Z15+Z18)*Assumpties!$C$34 -> 22.95959
B29: Support | C29: =C13*Assumpties!$C$36+C15*Assumpties!$C$37 -> 0.5 | D29: =D13*Assumpties!$C$36+D15*Assumpties!$C$37 -> 1 | E29: =E13*Assumpties!$C$36+E15*Assumpties!$C$37 -> 1.5 | F29: =F13*Assumpties!$C$36+F15*Assumpties!$C$37 -> 2 | G29: =G13*Assumpties!$C$36+G15*Assumpties!$C$37 -> 2.5 | H29: =H13*Assumpties!$C$36+H15*Assumpties!$C$37 -> 3 | I29: =I13*Assumpties!$C$36+I15*Assumpties!$C$37 -> 3 | J29: =J13*Assumpties!$C$36+J15*Assumpties!$C$37 -> 3 | ... Z29: =Z13*Assumpties!$C$36+Z15*Assumpties!$C$37 -> 10.5
B30: Vaste platformkosten | C30: =Assumpties!$C$35 -> 25 | D30: =Assumpties!$C$35 -> 25 | E30: =Assumpties!$C$35 -> 25 | F30: =Assumpties!$C$35 -> 25 | G30: =Assumpties!$C$35 -> 25 | H30: =Assumpties!$C$35 -> 25 | I30: =Assumpties!$C$35 -> 25 | J30: =Assumpties!$C$35 -> 25 | ... Z30: =Assumpties!$C$35 -> 25
B31: CAC | C31: =C9*Assumpties!$C$38 -> 8 | D31: =D9*Assumpties!$C$38 -> 8 | E31: =E9*Assumpties!$C$38 -> 8 | F31: =F9*Assumpties!$C$38 -> 8 | G31: =G9*Assumpties!$C$38 -> 8 | H31: =H9*Assumpties!$C$38 -> 8 | I31: =I9*Assumpties!$C$38 -> 8 | J31: =J9*Assumpties!$C$38 -> 8 | ... Z31: =Z9*Assumpties!$C$38 -> 32
B32: Netto winst per maand | C32: =C24-C28-C29-C30-C31 -> -12.39771 | D32: =D24-D28-D29-D30-D31 -> 17.65487 | E32: =E24-E28-E29-E30-E31 -> 38.25716 | F32: =F24-F28-F29-F30-F31 -> 68.30974 | G32: =G24-G28-G29-G30-G31 -> 88.91203 | H32: =H24-H28-H29-H30-H31 -> 109.51432 | I32: =I24-I28-I29-I30-I31 -> 109.51432 | J32: =J24-J28-J29-J30-J31 -> 109.51432 | ... Z32: =Z24-Z28-Z29-Z30-Z31 -> 451.25041
B33: Cumulatieve winst | C33: =C32 -> -12.39771 | D33: =C33+D32 -> 5.25716 | E33: =D33+E32 -> 43.51432 | F33: =E33+F32 -> 111.82406 | G33: =F33+G32 -> 200.73609 | H33: =G33+H32 -> 310.25041 | I33: =H33+I32 -> 419.76473 | J33: =I33+J32 -> 529.27905 | K33: =J33+K32 -> 638.79337 | ... Z33: =Y33+Z32 -> 4649.6551

Sheet Model C — Credits-only
A1: Model C — Credits-only (pure pay-as-you-go)
B2: Alle blauwe cellen op de Assumpties-sheet sturen dit model aan. MRR-rij = recurring; CumRev = totaal sinds maand 1.
B4: Maand → | C4: M1 | D4: M2 | E4: M3 | F4: M4 | G4: M5 | H4: M6 | I4: M7 | J4: M8 | K4: M9 | L4: M10 | M4: M11 | N4: M12 | O4: M13 | P4: M14 | Q4: M15 | R4: M16 | S4: M17 | T4: M18 | U4: M19 | V4: M20 | W4: M21 | X4: M22 | Y4: M23 | Z4: M24
A5: Acquisitie funnel
B6: Nieuwe Free signups (per maand) | C6: =Assumpties!$C$7 -> 30 | D6: =ROUND(C6*(1+Assumpties!$C$8),0) -> 32 | E6: =ROUND(D6*(1+Assumpties!$C$8),0) -> 35 | F6: =ROUND(E6*(1+Assumpties!$C$8),0) -> 38 | G6: =ROUND(F6*(1+Assumpties!$C$8),0) -> 41 | H6: =ROUND(G6*(1+Assumpties!$C$8),0) -> 44 | I6: =ROUND(H6*(1+Assumpties!$C$8),0) -> 48 | J6: =ROUND(I6*(1+Assumpties!$C$8),0) -> 52 | K6: =ROUND(J6*(1+Assumpties!$C$8),0) -> 56 | ... Z6: =ROUND(Y6*(1+Assumpties!$C$8),0) -> 177
B7: Cumulatieve Free signups | C7: =C6 -> 30 | D7: =C7+D6 -> 62 | E7: =D7+E6 -> 97 | F7: =E7+F6 -> 135 | G7: =F7+G6 -> 176 | H7: =G7+H6 -> 220 | I7: =H7+I6 -> 268 | J7: =I7+J6 -> 320 | K7: =J7+K6 -> 376 | ... Z7: =Y7+Z6 -> 2016
B8: Actieve Free users (na activatie) | C8: =ROUND(C7*Assumpties!$C$9,0) -> 17 | D8: =ROUND(D7*Assumpties!$C$9,0) -> 34 | E8: =ROUND(E7*Assumpties!$C$9,0) -> 53 | F8: =ROUND(F7*Assumpties!$C$9,0) -> 74 | G8: =ROUND(G7*Assumpties!$C$9,0) -> 97 | H8: =ROUND(H7*Assumpties!$C$9,0) -> 121 | I8: =ROUND(I7*Assumpties!$C$9,0) -> 147 | J8: =ROUND(J7*Assumpties!$C$9,0) -> 176 | ... Z8: =ROUND(Z7*Assumpties!$C$9,0) -> 1109
B9: Nieuwe paid conversions (per maand) | C9: =ROUND(C6*Assumpties!$C$9*Assumpties!$C$10,0) -> 1 | D9: =ROUND(D6*Assumpties!$C$9*Assumpties!$C$10,0) -> 1 | E9: =ROUND(E6*Assumpties!$C$9*Assumpties!$C$10,0) -> 1 | F9: =ROUND(F6*Assumpties!$C$9*Assumpties!$C$10,0) -> 1 | G9: =ROUND(G6*Assumpties!$C$9*Assumpties!$C$10,0) -> 1 | H9: =ROUND(H6*Assumpties!$C$9*Assumpties!$C$10,0) -> 1 | I9: =ROUND(I6*Assumpties!$C$9*Assumpties!$C$10,0) -> 1 | J9: =ROUND(J6*Assumpties!$C$9*Assumpties!$C$10,0) -> 1 | ... Z9: =ROUND(Z6*Assumpties!$C$9*Assumpties!$C$10,0) -> 4
A11: Geen abonnement — alleen credit-packs (€9,99 per 10 clips)
B12: Actieve credit-kopers (laatste 30 dagen) | C12: =C9 -> 1 | D12: =ROUND(C12*0.5+D9,0) -> 2 | E12: =ROUND(D12*0.5+E9,0) -> 2 | F12: =ROUND(E12*0.5+F9,0) -> 2 | G12: =ROUND(F12*0.5+G9,0) -> 2 | H12: =ROUND(G12*0.5+H9,0) -> 2 | I12: =ROUND(H12*0.5+I9,0) -> 2 | J12: =ROUND(I12*0.5+J9,0) -> 2 | K12: =ROUND(J12*0.5+K9,0) -> 2 | ... Z12: =ROUND(Y12*0.5+Z9,0) -> 8
B13: Gem. packs per actieve klant (per maand) | C13: 1.4 | D13: 1.4 | E13: 1.4 | F13: 1.4 | G13: 1.4 | H13: 1.4 | I13: 1.4 | J13: 1.4 | K13: 1.4 | L13: 1.4 | M13: 1.4 | N13: 1.4 | O13: 1.4 | P13: 1.4 | Q13: 1.4 | R13: 1.4 | S13: 1.4 | T13: 1.4 | U13: 1.4 | V13: 1.4 | W13: 1.4 | X13: 1.4 | Y13: 1.4 | Z13: 1.4
B14: Totaal credit-packs verkocht | C14: =ROUND(C12*C13,0) -> 1 | D14: =ROUND(D12*D13,0) -> 3 | E14: =ROUND(E12*E13,0) -> 3 | F14: =ROUND(F12*F13,0) -> 3 | G14: =ROUND(G12*G13,0) -> 3 | H14: =ROUND(H12*H13,0) -> 3 | I14: =ROUND(I12*I13,0) -> 3 | J14: =ROUND(J12*J13,0) -> 3 | ... Z14: =ROUND(Z12*Z13,0) -> 11
A16: Omzet (EUR)
B17: Totaal omzet | C17: =C14*Assumpties!$C$27 -> 9.99 | D17: =D14*Assumpties!$C$27 -> 29.97 | E17: =E14*Assumpties!$C$27 -> 29.97 | F17: =F14*Assumpties!$C$27 -> 29.97 | G17: =G14*Assumpties!$C$27 -> 29.97 | H17: =H14*Assumpties!$C$27 -> 29.97 | I17: =I14*Assumpties!$C$27 -> 29.97 | J17: =J14*Assumpties!$C$27 -> 29.97 | ... Z17: =Z14*Assumpties!$C$27 -> 109.89
B18: Cumulatieve omzet | C18: =C17 -> 9.99 | D18: =C18+D17 -> 39.96 | E18: =D18+E17 -> 69.93 | F18: =E18+F17 -> 99.9 | G18: =F18+G17 -> 129.87 | H18: =G18+H17 -> 159.84 | I18: =H18+I17 -> 189.81 | J18: =I18+J17 -> 219.78 | K18: =J18+K17 -> 249.75 | ... Z18: =Y18+Z17 -> 1228.77
A20: Netto winst
B21: Stripe fees | C21: =C17*Assumpties!$C$33+C14*Assumpties!$C$34 -> 0.53971 | D21: =D17*Assumpties!$C$33+D14*Assumpties!$C$34 -> 1.61913 | E21: =E17*Assumpties!$C$33+E14*Assumpties!$C$34 -> 1.61913 | F21: =F17*Assumpties!$C$33+F14*Assumpties!$C$34 -> 1.61913 | G21: =G17*Assumpties!$C$33+G14*Assumpties!$C$34 -> 1.61913 | H21: =H17*Assumpties!$C$33+H14*Assumpties!$C$34 -> 1.61913 | I21: =I17*Assumpties!$C$33+I14*Assumpties!$C$34 -> 1.61913 | J21: =J17*Assumpties!$C$33+J14*Assumpties!$C$34 -> 1.61913 | ... Z21: =Z17*Assumpties!$C$33+Z14*Assumpties!$C$34 -> 5.93681
B22: Support (lichter, geen sub) | C22: =C12*0.2 -> 0.2 | D22: =D12*0.2 -> 0.4 | E22: =E12*0.2 -> 0.4 | F22: =F12*0.2 -> 0.4 | G22: =G12*0.2 -> 0.4 | H22: =H12*0.2 -> 0.4 | I22: =I12*0.2 -> 0.4 | J22: =J12*0.2 -> 0.4 | ... Z22: =Z12*0.2 -> 1.6
B23: Vaste platformkosten | C23: =Assumpties!$C$35 -> 25 | D23: =Assumpties!$C$35 -> 25 | E23: =Assumpties!$C$35 -> 25 | F23: =Assumpties!$C$35 -> 25 | G23: =Assumpties!$C$35 -> 25 | H23: =Assumpties!$C$35 -> 25 | I23: =Assumpties!$C$35 -> 25 | J23: =Assumpties!$C$35 -> 25 | ... Z23: =Assumpties!$C$35 -> 25
B24: CAC | C24: =C9*Assumpties!$C$38 -> 8 | D24: =D9*Assumpties!$C$38 -> 8 | E24: =E9*Assumpties!$C$38 -> 8 | F24: =F9*Assumpties!$C$38 -> 8 | G24: =G9*Assumpties!$C$38 -> 8 | H24: =H9*Assumpties!$C$38 -> 8 | I24: =I9*Assumpties!$C$38 -> 8 | J24: =J9*Assumpties!$C$38 -> 8 | ... Z24: =Z9*Assumpties!$C$38 -> 32
B25: Netto winst per maand | C25: =C17-C21-C22-C23-C24 -> -23.74971 | D25: =D17-D21-D22-D23-D24 -> -5.04913 | E25: =E17-E21-E22-E23-E24 -> -5.04913 | F25: =F17-F21-F22-F23-F24 -> -5.04913 | G25: =G17-G21-G22-G23-G24 -> -5.04913 | H25: =H17-H21-H22-H23-H24 -> -5.04913 | I25: =I17-I21-I22-I23-I24 -> -5.04913 | J25: =J17-J21-J22-J23-J24 -> -5.04913 | ... Z25: =Z17-Z21-Z22-Z23-Z24 -> 45.35319
B26: Cumulatieve winst | C26: =C25 -> -23.74971 | D26: =C26+D25 -> -28.79884 | E26: =D26+E25 -> -33.84797 | F26: =E26+F25 -> -38.8971 | G26: =F26+G25 -> -43.94623 | H26: =G26+H25 -> -48.99536 | I26: =H26+I25 -> -54.04449 | J26: =I26+J25 -> -59.09362 | K26: =J26+K25 -> -64.14275 | ... Z26: =Y26+Z25 -> 185.18567

Sheet Model D — Freemium + Pro+
A1: Model D — Freemium + Pro+ (mid-tier)
B2: Alle blauwe cellen op de Assumpties-sheet sturen dit model aan. MRR-rij = recurring; CumRev = totaal sinds maand 1.
B4: Maand → | C4: M1 | D4: M2 | E4: M3 | F4: M4 | G4: M5 | H4: M6 | I4: M7 | J4: M8 | K4: M9 | L4: M10 | M4: M11 | N4: M12 | O4: M13 | P4: M14 | Q4: M15 | R4: M16 | S4: M17 | T4: M18 | U4: M19 | V4: M20 | W4: M21 | X4: M22 | Y4: M23 | Z4: M24
A5: Acquisitie funnel
B6: Nieuwe Free signups (per maand) | C6: =Assumpties!$C$7 -> 30 | D6: =ROUND(C6*(1+Assumpties!$C$8),0) -> 32 | E6: =ROUND(D6*(1+Assumpties!$C$8),0) -> 35 | F6: =ROUND(E6*(1+Assumpties!$C$8),0) -> 38 | G6: =ROUND(F6*(1+Assumpties!$C$8),0) -> 41 | H6: =ROUND(G6*(1+Assumpties!$C$8),0) -> 44 | I6: =ROUND(H6*(1+Assumpties!$C$8),0) -> 48 | J6: =ROUND(I6*(1+Assumpties!$C$8),0) -> 52 | K6: =ROUND(J6*(1+Assumpties!$C$8),0) -> 56 | ... Z6: =ROUND(Y6*(1+Assumpties!$C$8),0) -> 177
B7: Cumulatieve Free signups | C7: =C6 -> 30 | D7: =C7+D6 -> 62 | E7: =D7+E6 -> 97 | F7: =E7+F6 -> 135 | G7: =F7+G6 -> 176 | H7: =G7+H6 -> 220 | I7: =H7+I6 -> 268 | J7: =I7+J6 -> 320 | K7: =J7+K6 -> 376 | ... Z7: =Y7+Z6 -> 2016
B8: Actieve Free users (na activatie) | C8: =ROUND(C7*Assumpties!$C$9,0) -> 17 | D8: =ROUND(D7*Assumpties!$C$9,0) -> 34 | E8: =ROUND(E7*Assumpties!$C$9,0) -> 53 | F8: =ROUND(F7*Assumpties!$C$9,0) -> 74 | G8: =ROUND(G7*Assumpties!$C$9,0) -> 97 | H8: =ROUND(H7*Assumpties!$C$9,0) -> 121 | I8: =ROUND(I7*Assumpties!$C$9,0) -> 147 | J8: =ROUND(J7*Assumpties!$C$9,0) -> 176 | ... Z8: =ROUND(Z7*Assumpties!$C$9,0) -> 1109
B9: Nieuwe paid conversions (per maand) | C9: =ROUND(C6*Assumpties!$C$9*Assumpties!$C$10,0) -> 1 | D9: =ROUND(D6*Assumpties!$C$9*Assumpties!$C$10,0) -> 1 | E9: =ROUND(E6*Assumpties!$C$9*Assumpties!$C$10,0) -> 1 | F9: =ROUND(F6*Assumpties!$C$9*Assumpties!$C$10,0) -> 1 | G9: =ROUND(G6*Assumpties!$C$9*Assumpties!$C$10,0) -> 1 | H9: =ROUND(H6*Assumpties!$C$9*Assumpties!$C$10,0) -> 1 | I9: =ROUND(I6*Assumpties!$C$9*Assumpties!$C$10,0) -> 1 | J9: =ROUND(J6*Assumpties!$C$9*Assumpties!$C$10,0) -> 1 | ... Z9: =ROUND(Z6*Assumpties!$C$9*Assumpties!$C$10,0) -> 4
A11: 3 betaalde tiers: Pro €21,99 (55%) / Pro+ €49 (30%) / Studio €200 (15%)
B12: Nieuwe Pro klanten (55% van paid) | C12: =ROUND(C9*0.55,0) -> 1 | D12: =ROUND(D9*0.55,0) -> 1 | E12: =ROUND(E9*0.55,0) -> 1 | F12: =ROUND(F9*0.55,0) -> 1 | G12: =ROUND(G9*0.55,0) -> 1 | H12: =ROUND(H9*0.55,0) -> 1 | I12: =ROUND(I9*0.55,0) -> 1 | J12: =ROUND(J9*0.55,0) -> 1 | ... Z12: =ROUND(Z9*0.55,0) -> 2
B13: Actieve Pro klanten | C13: =C12 -> 1 | D13: =ROUND(C13*(1-Assumpties!$C$17)+D12,0) -> 2 | E13: =ROUND(D13*(1-Assumpties!$C$17)+E12,0) -> 3 | F13: =ROUND(E13*(1-Assumpties!$C$17)+F12,0) -> 4 | G13: =ROUND(F13*(1-Assumpties!$C$17)+G12,0) -> 5 | H13: =ROUND(G13*(1-Assumpties!$C$17)+H12,0) -> 6 | I13: =ROUND(H13*(1-Assumpties!$C$17)+I12,0) -> 6 | J13: =ROUND(I13*(1-Assumpties!$C$17)+J12,0) -> 6 | K13: =ROUND(J13*(1-Assumpties!$C$17)+K12,0) -> 6 | ... Z13: =ROUND(Y13*(1-Assumpties!$C$17)+Z12,0) -> 12
B14: Nieuwe Pro+ klanten (30%) | C14: =ROUND(C9*0.3,0) -> 0 | D14: =ROUND(D9*0.3,0) -> 0 | E14: =ROUND(E9*0.3,0) -> 0 | F14: =ROUND(F9*0.3,0) -> 0 | G14: =ROUND(G9*0.3,0) -> 0 | H14: =ROUND(H9*0.3,0) -> 0 | I14: =ROUND(I9*0.3,0) -> 0 | J14: =ROUND(J9*0.3,0) -> 0 | ... Z14: =ROUND(Z9*0.3,0) -> 1
B15: Actieve Pro+ klanten | C15: =C14 -> 0 | D15: =ROUND(C15*(1-Assumpties!$C$19)+D14,0) -> 0 | E15: =ROUND(D15*(1-Assumpties!$C$19)+E14,0) -> 0 | F15: =ROUND(E15*(1-Assumpties!$C$19)+F14,0) -> 0 | G15: =ROUND(F15*(1-Assumpties!$C$19)+G14,0) -> 0 | H15: =ROUND(G15*(1-Assumpties!$C$19)+H14,0) -> 0 | I15: =ROUND(H15*(1-Assumpties!$C$19)+I14,0) -> 0 | J15: =ROUND(I15*(1-Assumpties!$C$19)+J14,0) -> 0 | K15: =ROUND(J15*(1-Assumpties!$C$19)+K14,0) -> 0 | ... Z15: =ROUND(Y15*(1-Assumpties!$C$19)+Z14,0) -> 7
B16: Nieuwe Studio klanten (15%) | C16: =ROUND(C9*0.15,0) -> 0 | D16: =ROUND(D9*0.15,0) -> 0 | E16: =ROUND(E9*0.15,0) -> 0 | F16: =ROUND(F9*0.15,0) -> 0 | G16: =ROUND(G9*0.15,0) -> 0 | H16: =ROUND(H9*0.15,0) -> 0 | I16: =ROUND(I9*0.15,0) -> 0 | J16: =ROUND(J9*0.15,0) -> 0 | ... Z16: =ROUND(Z9*0.15,0) -> 1
B17: Actieve Studio klanten | C17: =C16 -> 0 | D17: =ROUND(C17*(1-Assumpties!$C$18)+D16,0) -> 0 | E17: =ROUND(D17*(1-Assumpties!$C$18)+E16,0) -> 0 | F17: =ROUND(E17*(1-Assumpties!$C$18)+F16,0) -> 0 | G17: =ROUND(F17*(1-Assumpties!$C$18)+G16,0) -> 0 | H17: =ROUND(G17*(1-Assumpties!$C$18)+H16,0) -> 0 | I17: =ROUND(H17*(1-Assumpties!$C$18)+I16,0) -> 0 | J17: =ROUND(I17*(1-Assumpties!$C$18)+J16,0) -> 0 | K17: =ROUND(J17*(1-Assumpties!$C$18)+K16,0) -> 0 | ... Z17: =ROUND(Y17*(1-Assumpties!$C$18)+Z16,0) -> 2
A19: Omzet
B20: Pro MRR | C20: =C13*Assumpties!$C$24 -> 21.99 | D20: =D13*Assumpties!$C$24 -> 43.98 | E20: =E13*Assumpties!$C$24 -> 65.97 | F20: =F13*Assumpties!$C$24 -> 87.96 | G20: =G13*Assumpties!$C$24 -> 109.95 | H20: =H13*Assumpties!$C$24 -> 131.94 | I20: =I13*Assumpties!$C$24 -> 131.94 | J20: =J13*Assumpties!$C$24 -> 131.94 | ... Z20: =Z13*Assumpties!$C$24 -> 263.88
B21: Pro+ MRR | C21: =C15*Assumpties!$C$26 -> 0 | D21: =D15*Assumpties!$C$26 -> 0 | E21: =E15*Assumpties!$C$26 -> 0 | F21: =F15*Assumpties!$C$26 -> 0 | G21: =G15*Assumpties!$C$26 -> 0 | H21: =H15*Assumpties!$C$26 -> 0 | I21: =I15*Assumpties!$C$26 -> 0 | J21: =J15*Assumpties!$C$26 -> 0 | ... Z21: =Z15*Assumpties!$C$26 -> 343
B22: Studio MRR | C22: =C17*Assumpties!$C$25 -> 0 | D22: =D17*Assumpties!$C$25 -> 0 | E22: =E17*Assumpties!$C$25 -> 0 | F22: =F17*Assumpties!$C$25 -> 0 | G22: =G17*Assumpties!$C$25 -> 0 | H22: =H17*Assumpties!$C$25 -> 0 | I22: =I17*Assumpties!$C$25 -> 0 | J22: =J17*Assumpties!$C$25 -> 0 | ... Z22: =Z17*Assumpties!$C$25 -> 400
B23: Totaal MRR | C23: =C20+C21+C22 -> 21.99 | D23: =D20+D21+D22 -> 43.98 | E23: =E20+E21+E22 -> 65.97 | F23: =F20+F21+F22 -> 87.96 | G23: =G20+G21+G22 -> 109.95 | H23: =H20+H21+H22 -> 131.94 | I23: =I20+I21+I22 -> 131.94 | J23: =J20+J21+J22 -> 131.94 | ... Z23: =Z20+Z21+Z22 -> 1006.88
B24: Cumulatieve omzet | C24: =C23 -> 21.99 | D24: =C24+D23 -> 65.97 | E24: =D24+E23 -> 131.94 | F24: =E24+F23 -> 219.9 | G24: =F24+G23 -> 329.85 | H24: =G24+H23 -> 461.79 | I24: =H24+I23 -> 593.73 | J24: =I24+J23 -> 725.67 | K24: =J24+K23 -> 857.61 | ... Z24: =Y24+Z23 -> 7328.5
A26: Netto winst
B27: Stripe fees | C27: =C23*Assumpties!$C$33+(C13+C15+C17)*Assumpties!$C$34 -> 0.88771 | D27: =D23*Assumpties!$C$33+(D13+D15+D17)*Assumpties!$C$34 -> 1.77542 | E27: =E23*Assumpties!$C$33+(E13+E15+E17)*Assumpties!$C$34 -> 2.66313 | F27: =F23*Assumpties!$C$33+(F13+F15+F17)*Assumpties!$C$34 -> 3.55084 | G27: =G23*Assumpties!$C$33+(G13+G15+G17)*Assumpties!$C$34 -> 4.43855 | H27: =H23*Assumpties!$C$33+(H13+H15+H17)*Assumpties!$C$34 -> 5.32626 | I27: =I23*Assumpties!$C$33+(I13+I15+I17)*Assumpties!$C$34 -> 5.32626 | J27: =J23*Assumpties!$C$33+(J13+J15+J17)*Assumpties!$C$34 -> 5.32626 | ... Z27: =Z23*Assumpties!$C$33+(Z13+Z15+Z17)*Assumpties!$C$34 -> 34.44952
B28: Support | C28: =(C13+C15)*Assumpties!$C$36+C17*Assumpties!$C$37 -> 0.5 | D28: =(D13+D15)*Assumpties!$C$36+D17*Assumpties!$C$37 -> 1 | E28: =(E13+E15)*Assumpties!$C$36+E17*Assumpties!$C$37 -> 1.5 | F28: =(F13+F15)*Assumpties!$C$36+F17*Assumpties!$C$37 -> 2 | G28: =(G13+G15)*Assumpties!$C$36+G17*Assumpties!$C$37 -> 2.5 | H28: =(H13+H15)*Assumpties!$C$36+H17*Assumpties!$C$37 -> 3 | I28: =(I13+I15)*Assumpties!$C$36+I17*Assumpties!$C$37 -> 3 | J28: =(J13+J15)*Assumpties!$C$36+J17*Assumpties!$C$37 -> 3 | ... Z28: =(Z13+Z15)*Assumpties!$C$36+Z17*Assumpties!$C$37 -> 19.5
B29: Vaste platformkosten | C29: =Assumpties!$C$35 -> 25 | D29: =Assumpties!$C$35 -> 25 | E29: =Assumpties!$C$35 -> 25 | F29: =Assumpties!$C$35 -> 25 | G29: =Assumpties!$C$35 -> 25 | H29: =Assumpties!$C$35 -> 25 | I29: =Assumpties!$C$35 -> 25 | J29: =Assumpties!$C$35 -> 25 | ... Z29: =Assumpties!$C$35 -> 25
B30: CAC | C30: =C9*Assumpties!$C$38 -> 8 | D30: =D9*Assumpties!$C$38 -> 8 | E30: =E9*Assumpties!$C$38 -> 8 | F30: =F9*Assumpties!$C$38 -> 8 | G30: =G9*Assumpties!$C$38 -> 8 | H30: =H9*Assumpties!$C$38 -> 8 | I30: =I9*Assumpties!$C$38 -> 8 | J30: =J9*Assumpties!$C$38 -> 8 | ... Z30: =Z9*Assumpties!$C$38 -> 32
B31: Netto winst per maand | C31: =C23-C27-C28-C29-C30 -> -12.39771 | D31: =D23-D27-D28-D29-D30 -> 8.20458 | E31: =E23-E27-E28-E29-E30 -> 28.80687 | F31: =F23-F27-F28-F29-F30 -> 49.40916 | G31: =G23-G27-G28-G29-G30 -> 70.01145 | H31: =H23-H27-H28-H29-H30 -> 90.61374 | I31: =I23-I27-I28-I29-I30 -> 90.61374 | J31: =J23-J27-J28-J29-J30 -> 90.61374 | ... Z31: =Z23-Z27-Z28-Z29-Z30 -> 895.93048
B32: Cumulatieve winst | C32: =C31 -> -12.39771 | D32: =C32+D31 -> -4.19313 | E32: =D32+E31 -> 24.61374 | F32: =E32+F31 -> 74.0229 | G32: =F32+G31 -> 144.03435 | H32: =G32+H31 -> 234.64809 | I32: =H32+I31 -> 325.26183 | J32: =I32+J31 -> 415.87557 | K32: =J32+K31 -> 506.48931 | ... Z32: =Y32+Z31 -> 5975.2235

Sheet Model E — Outcome-based
A1: Model E — Outcome-based (basis €4,99 + €2,50/virale clip)
B2: Alle blauwe cellen op de Assumpties-sheet sturen dit model aan. MRR-rij = recurring; CumRev = totaal sinds maand 1.
B4: Maand → | C4: M1 | D4: M2 | E4: M3 | F4: M4 | G4: M5 | H4: M6 | I4: M7 | J4: M8 | K4: M9 | L4: M10 | M4: M11 | N4: M12 | O4: M13 | P4: M14 | Q4: M15 | R4: M16 | S4: M17 | T4: M18 | U4: M19 | V4: M20 | W4: M21 | X4: M22 | Y4: M23 | Z4: M24
A5: Acquisitie funnel
B6: Nieuwe Free signups (per maand) | C6: =Assumpties!$C$7 -> 30 | D6: =ROUND(C6*(1+Assumpties!$C$8),0) -> 32 | E6: =ROUND(D6*(1+Assumpties!$C$8),0) -> 35 | F6: =ROUND(E6*(1+Assumpties!$C$8),0) -> 38 | G6: =ROUND(F6*(1+Assumpties!$C$8),0) -> 41 | H6: =ROUND(G6*(1+Assumpties!$C$8),0) -> 44 | I6: =ROUND(H6*(1+Assumpties!$C$8),0) -> 48 | J6: =ROUND(I6*(1+Assumpties!$C$8),0) -> 52 | K6: =ROUND(J6*(1+Assumpties!$C$8),0) -> 56 | ... Z6: =ROUND(Y6*(1+Assumpties!$C$8),0) -> 177
B7: Cumulatieve Free signups | C7: =C6 -> 30 | D7: =C7+D6 -> 62 | E7: =D7+E6 -> 97 | F7: =E7+F6 -> 135 | G7: =F7+G6 -> 176 | H7: =G7+H6 -> 220 | I7: =H7+I6 -> 268 | J7: =I7+J6 -> 320 | K7: =J7+K6 -> 376 | ... Z7: =Y7+Z6 -> 2016
B8: Actieve Free users (na activatie) | C8: =ROUND(C7*Assumpties!$C$9,0) -> 17 | D8: =ROUND(D7*Assumpties!$C$9,0) -> 34 | E8: =ROUND(E7*Assumpties!$C$9,0) -> 53 | F8: =ROUND(F7*Assumpties!$C$9,0) -> 74 | G8: =ROUND(G7*Assumpties!$C$9,0) -> 97 | H8: =ROUND(H7*Assumpties!$C$9,0) -> 121 | I8: =ROUND(I7*Assumpties!$C$9,0) -> 147 | J8: =ROUND(J7*Assumpties!$C$9,0) -> 176 | ... Z8: =ROUND(Z7*Assumpties!$C$9,0) -> 1109
B9: Nieuwe paid conversions (per maand) | C9: =ROUND(C6*Assumpties!$C$9*Assumpties!$C$10,0) -> 1 | D9: =ROUND(D6*Assumpties!$C$9*Assumpties!$C$10,0) -> 1 | E9: =ROUND(E6*Assumpties!$C$9*Assumpties!$C$10,0) -> 1 | F9: =ROUND(F6*Assumpties!$C$9*Assumpties!$C$10,0) -> 1 | G9: =ROUND(G6*Assumpties!$C$9*Assumpties!$C$10,0) -> 1 | H9: =ROUND(H6*Assumpties!$C$9*Assumpties!$C$10,0) -> 1 | I9: =ROUND(I6*Assumpties!$C$9*Assumpties!$C$10,0) -> 1 | J9: =ROUND(J6*Assumpties!$C$9*Assumpties!$C$10,0) -> 1 | ... Z9: =ROUND(Z6*Assumpties!$C$9*Assumpties!$C$10,0) -> 4
A11: Basis €4,99 + €2,50 per virale clip (>10k views). Hogere conversie verwacht.
B12: Nieuwe paid (2x baseline door lage instap) | C12: =C9*2 -> 2 | D12: =D9*2 -> 2 | E12: =E9*2 -> 2 | F12: =F9*2 -> 2 | G12: =G9*2 -> 2 | H12: =H9*2 -> 2 | I12: =I9*2 -> 2 | J12: =J9*2 -> 2 | ... Z12: =Z9*2 -> 8
B13: Actieve abonnees (8% churn) | C13: =C12 -> 2 | D13: =ROUND(C13*0.92+D12,0) -> 4 | E13: =ROUND(D13*0.92+E12,0) -> 6 | F13: =ROUND(E13*0.92+F12,0) -> 8 | G13: =ROUND(F13*0.92+G12,0) -> 9 | H13: =ROUND(G13*0.92+H12,0) -> 10 | I13: =ROUND(H13*0.92+I12,0) -> 11 | J13: =ROUND(I13*0.92+J12,0) -> 12 | K13: =ROUND(J13*0.92+K12,0) -> 13 | ... Z13: =ROUND(Y13*0.92+Z12,0) -> 52
B14: Gem. virale clips per actieve abonnee/mnd | C14: 0.8 | D14: 0.8 | E14: 0.8 | F14: 0.8 | G14: 0.8 | H14: 0.8 | I14: 0.8 | J14: 0.8 | K14: 0.8 | L14: 0.8 | M14: 0.8 | N14: 0.8 | O14: 0.8 | P14: 0.8 | Q14: 0.8 | R14: 0.8 | S14: 0.8 | T14: 0.8 | U14: 0.8 | V14: 0.8 | W14: 0.8 | X14: 0.8 | Y14: 0.8 | Z14: 0.8
B15: Totaal virale clips (fee-triggering) | C15: =ROUND(C13*C14,0) -> 2 | D15: =ROUND(D13*D14,0) -> 3 | E15: =ROUND(E13*E14,0) -> 5 | F15: =ROUND(F13*F14,0) -> 6 | G15: =ROUND(G13*G14,0) -> 7 | H15: =ROUND(H13*H14,0) -> 8 | I15: =ROUND(I13*I14,0) -> 9 | J15: =ROUND(J13*J14,0) -> 10 | ... Z15: =ROUND(Z13*Z14,0) -> 42
A17: Omzet
B18: Basis-fee omzet | C18: =C13*Assumpties!$C$29 -> 9.98 | D18: =D13*Assumpties!$C$29 -> 19.96 | E18: =E13*Assumpties!$C$29 -> 29.94 | F18: =F13*Assumpties!$C$29 -> 39.92 | G18: =G13*Assumpties!$C$29 -> 44.91 | H18: =H13*Assumpties!$C$29 -> 49.9 | I18: =I13*Assumpties!$C$29 -> 54.89 | J18: =J13*Assumpties!$C$29 -> 59.88 | ... Z18: =Z13*Assumpties!$C$29 -> 259.48
B19: Outcome-fee omzet | C19: =C15*Assumpties!$C$28 -> 5 | D19: =D15*Assumpties!$C$28 -> 7.5 | E19: =E15*Assumpties!$C$28 -> 12.5 | F19: =F15*Assumpties!$C$28 -> 15 | G19: =G15*Assumpties!$C$28 -> 17.5 | H19: =H15*Assumpties!$C$28 -> 20 | I19: =I15*Assumpties!$C$28 -> 22.5 | J19: =J15*Assumpties!$C$28 -> 25 | ... Z19: =Z15*Assumpties!$C$28 -> 105
B20: Totaal omzet | C20: =C18+C19 -> 14.98 | D20: =D18+D19 -> 27.46 | E20: =E18+E19 -> 42.44 | F20: =F18+F19 -> 54.92 | G20: =G18+G19 -> 62.41 | H20: =H18+H19 -> 69.9 | I20: =I18+I19 -> 77.39 | J20: =J18+J19 -> 84.88 | ... Z20: =Z18+Z19 -> 364.48
B21: Cumulatieve omzet | C21: =C20 -> 14.98 | D21: =C21+D20 -> 42.44 | E21: =D21+E20 -> 84.88 | F21: =E21+F20 -> 139.8 | G21: =F21+G20 -> 202.21 | H21: =G21+H20 -> 272.11 | I21: =H21+I20 -> 349.5 | J21: =I21+J20 -> 434.38 | K21: =J21+K20 -> 524.25 | ... Z21: =Y21+Z20 -> 3744.64
A23: Netto winst
B24: Stripe fees | C24: =C20*Assumpties!$C$33+(C13+C15)*Assumpties!$C$34 -> 1.43442 | D24: =D20*Assumpties!$C$33+(D13+D15)*Assumpties!$C$34 -> 2.54634 | E24: =E20*Assumpties!$C$33+(E13+E15)*Assumpties!$C$34 -> 3.98076 | F24: =F20*Assumpties!$C$33+(F13+F15)*Assumpties!$C$34 -> 5.09268 | G24: =G20*Assumpties!$C$33+(G13+G15)*Assumpties!$C$34 -> 5.80989 | H24: =H20*Assumpties!$C$33+(H13+H15)*Assumpties!$C$34 -> 6.5271 | I24: =I20*Assumpties!$C$33+(I13+I15)*Assumpties!$C$34 -> 7.24431 | J24: =J20*Assumpties!$C$33+(J13+J15)*Assumpties!$C$34 -> 7.96152 | ... Z24: =Z20*Assumpties!$C$33+(Z13+Z15)*Assumpties!$C$34 -> 34.06992
B25: View-tracking infra (per actieve) | C25: =C13*0.4 -> 0.8 | D25: =D13*0.4 -> 1.6 | E25: =E13*0.4 -> 2.4 | F25: =F13*0.4 -> 3.2 | G25: =G13*0.4 -> 3.6 | H25: =H13*0.4 -> 4 | I25: =I13*0.4 -> 4.4 | J25: =J13*0.4 -> 4.8 | ... Z25: =Z13*0.4 -> 20.8
B26: Support | C26: =C13*Assumpties!$C$36 -> 1 | D26: =D13*Assumpties!$C$36 -> 2 | E26: =E13*Assumpties!$C$36 -> 3 | F26: =F13*Assumpties!$C$36 -> 4 | G26: =G13*Assumpties!$C$36 -> 4.5 | H26: =H13*Assumpties!$C$36 -> 5 | I26: =I13*Assumpties!$C$36 -> 5.5 | J26: =J13*Assumpties!$C$36 -> 6 | ... Z26: =Z13*Assumpties!$C$36 -> 26
B27: Vaste platformkosten | C27: =Assumpties!$C$35 -> 25 | D27: =Assumpties!$C$35 -> 25 | E27: =Assumpties!$C$35 -> 25 | F27: =Assumpties!$C$35 -> 25 | G27: =Assumpties!$C$35 -> 25 | H27: =Assumpties!$C$35 -> 25 | I27: =Assumpties!$C$35 -> 25 | J27: =Assumpties!$C$35 -> 25 | ... Z27: =Assumpties!$C$35 -> 25
B28: CAC | C28: =C12*Assumpties!$C$38 -> 16 | D28: =D12*Assumpties!$C$38 -> 16 | E28: =E12*Assumpties!$C$38 -> 16 | F28: =F12*Assumpties!$C$38 -> 16 | G28: =G12*Assumpties!$C$38 -> 16 | H28: =H12*Assumpties!$C$38 -> 16 | I28: =I12*Assumpties!$C$38 -> 16 | J28: =J12*Assumpties!$C$38 -> 16 | ... Z28: =Z12*Assumpties!$C$38 -> 64
B29: Netto winst per maand | C29: =C20-C24-C25-C26-C27-C28 -> -29.25442 | D29: =D20-D24-D25-D26-D27-D28 -> -19.68634 | E29: =E20-E24-E25-E26-E27-E28 -> -7.94076 | F29: =F20-F24-F25-F26-F27-F28 -> 1.62732 | G29: =G20-G24-G25-G26-G27-G28 -> 7.50011 | H29: =H20-H24-H25-H26-H27-H28 -> 13.3729 | I29: =I20-I24-I25-I26-I27-I28 -> 19.24569 | J29: =J20-J24-J25-J26-J27-J28 -> 25.11848 | ... Z29: =Z20-Z24-Z25-Z26-Z27-Z28 -> 194.61008
B30: Cumulatieve winst | C30: =C29 -> -29.25442 | D30: =C30+D29 -> -48.94076 | E30: =D30+E29 -> -56.88152 | F30: =E30+F29 -> -55.2542 | G30: =F30+G29 -> -47.75409 | H30: =G30+H29 -> -34.38119 | I30: =H30+I29 -> -15.1355 | J30: =I30+J29 -> 9.98298 | K30: =J30+K29 -> 38.79675 | ... Z30: =Y30+Z29 -> 1592.6454

Sheet Vergelijking
A1: Vergelijking — welk model levert wanneer het meest op?
B2: Alle bedragen in EUR. Cijfers verwijzen direct naar de Model-sheets — pas Assumpties aan en alles herrekent.
B4: Metric | C4: A: Current | D4: B: Hybride | E4: C: Credits | F4: D: Pro+ | G4: E: Outcome
B5: MRR / Total Revenue maand 6 | C5: ='Model A — Current Tiers'!H20 -> 131.94 | D5: ='Model B — Hybride'!H24 -> 151.92 | E5: ='Model C — Credits-only'!H17 -> 29.97 | F5: ='Model D — Freemium + Pro+'!H23 -> 131.94 | G5: ='Model E — Outcome-based'!H20 -> 69.9
B6: MRR / Total Revenue maand 12 | C6: ='Model A — Current Tiers'!N20 -> 153.93 | D6: ='Model B — Hybride'!N24 -> 183.9 | E6: ='Model C — Credits-only'!N17 -> 39.96 | F6: ='Model D — Freemium + Pro+'!N23 -> 180.94 | G6: ='Model E — Outcome-based'!N20 -> 124.82
B7: MRR / Total Revenue maand 24 | C7: ='Model A — Current Tiers'!Z20 -> 461.79 | D7: ='Model B — Hybride'!Z24 -> 541.71 | E7: ='Model C — Credits-only'!Z17 -> 109.89 | F7: ='Model D — Freemium + Pro+'!Z23 -> 1006.88 | G7: ='Model E — Outcome-based'!Z20 -> 364.48
B8: Cum. omzet eind jaar 1 (M12) | C8: ='Model A — Current Tiers'!N21 -> 1275.42 | D8: ='Model B — Hybride'!N25 -> 1485.21 | E8: ='Model C — Credits-only'!N18 -> 349.65 | F8: ='Model D — Freemium + Pro+'!N24 -> 1302.43 | G8: ='Model E — Outcome-based'!N21 -> 851.28
B9: Cum. omzet eind jaar 2 (M24) | C9: ='Model A — Current Tiers'!Z21 -> 5079.69 | D9: ='Model B — Hybride'!Z25 -> 5978.79 | E9: ='Model C — Credits-only'!Z18 -> 1228.77 | F9: ='Model D — Freemium + Pro+'!Z24 -> 7328.5 | G9: ='Model E — Outcome-based'!Z21 -> 3744.64
B10: Cum. winst eind jaar 1 | C10: ='Model A — Current Tiers'!N29 -> 790.93282 | D10: ='Model B — Hybride'!N33 -> 989.38891 | E10: ='Model C — Credits-only'!N26 -> -78.03985 | F10: ='Model D — Freemium + Pro+'!N32 -> 817.15953 | G10: ='Model E — Outcome-based'!N30 -> 154.04288
B11: Cum. winst eind jaar 2 | C11: ='Model A — Current Tiers'!Z29 -> 3799.129 | D11: ='Model B — Hybride'!Z33 -> 4649.6551 | E11: ='Model C — Credits-only'!Z26 -> 185.18567 | F11: ='Model D — Freemium + Pro+'!Z32 -> 5975.2235 | G11: ='Model E — Outcome-based'!Z30 -> 1592.6454
B12: Netto winstmarge maand 24 | C12: =IF('Model A — Current Tiers'!Z20=0,0,'Model A — Current Tiers'!Z28/'Model A — Current Tiers'!Z20) -> 0.81346086 | D12: =IF('Model B — Hybride'!Z24=0,0,'Model B — Hybride'!Z32/'Model B — Hybride'!Z24) -> 0.83301104 | E12: =IF('Model C — Credits-only'!Z17=0,0,'Model C — Credits-only'!Z25/'Model C — Credits-only'!Z17) -> 0.41271444 | F12: =IF('Model D — Freemium + Pro+'!Z23=0,0,'Model D — Freemium + Pro+'!Z31/'Model D — Freemium + Pro+'!Z23) -> 0.8898086 | G12: =IF('Model E — Outcome-based'!Z20=0,0,'Model E — Outcome-based'!Z29/'Model E — Outcome-based'!Z20) -> 0.53393898
A14: Korte vs. lange termijn — beste keuze per fase
B15: Fase / scenario | C15: Aanbeveling
B16: Maand 0-3 (snelle revenue) | C16: Model B — hybride. Behoudt €21,99-prijspunt + credit-packs vangen pieken op. Geen breaking change voor huidige users.
B17: Maand 3-12 (scale, lifestyle target) | C17: Model D — Pro+ tier vangt mid-market. ARPU stijgt 25-40% zonder churn-risico op Pro.
B18: Maand 12-24 (investor-ready / Series A) | C18: Model B of D — investeerders waarderen voorspelbare recurring revenue + uplift via expansion (NRR>120%).
B19: Experiment (op zijspoor) | C19: Model E — outcome-based als referrabel verhaal voor PR/investeerders, maar vereist view-tracking infra (Phase 6+).
B20: Te vermijden | C20: Model C — pure credits. Geen NRR, lage valuation-multiple, mass-market alleen zinvol bij 10k+ MAU.

Sheet Feedback Rewards
A1: Feedback-rewards economie
B2: Hoe duur is het om gebruikers credits te geven voor feedback? En wat levert het op?
A4: Programma-design
B5: Programma | C5: Geef Free-users 1 extra set credit voor een ingestuurde feedback-form (max 1/30dgn). Pro-users: 2 extra sets of €5 korting op volgend pack.
B6: Doel | C6: (1) Productinsights, (2) Free→Paid conversie verhogen, (3) Loyale community bouwen waaruit ambassadors voortkomen.
B7: Mechaniek | C7: In-app widget na clip-export ('Wat ging er goed/mis?'). Beloning automatisch toegekend bij ≥3 zinnen + categorie-tag.
B8: Frictie laag | C8: Geen formulier-pagina; inline form direct in editor. Closed-loop: Sjuul reageert binnen 14 dgn (research toont dit verdubbelt deelnamerate).
A10: Kosten-baten model
B11: Parameter | C11: Waarde | D11: Eenheid | E11: Toelichting
B12: Actieve Free users na maand 6 (lookup) | C12: ='Model B — Hybride'!H7 -> 220 | D12: users | E12: Komt uit Model B regel 'Actieve Free users'
B13: Deelnameratio aan feedback-programma | C13: 0.15 | D13: % | E13: 15% is bovenwaarde — research zegt 5-20% bij gerichte triggers
B14: Aantal feedback-submissions / maand | C14: =ROUND(C12*C13,0) -> 33 | D14: subm. | E14: Berekend
B15: Beloning per Free submission (in credits) | C15: 1 | D15: set | E15: Marginale kostprijs ≈ €0 (lokale processing)
B16: Geschatte kostprijs per Free credit | C16: 0.05 | D16: EUR | E16: Stripe/Supabase overhead per extra job
B17: Totale kosten van programma (per maand) | C17: =C14*C15*C16 -> 1.65 | D17: EUR | E17: Berekend
B18: Conversie-uplift Free→Paid door programma | C18: 0.3 | D18: % | E18: +30% conversie bij actieve deelnemers (Userpilot 2026)
B19: Extra paid conversies per maand | C19: =ROUND(C14*Assumpties!$C$10*C18,0) -> 0 | D19: users | E19: Berekend
B20: Extra MRR-uplift (EUR/mnd, Pro-prijs) | C20: =C19*Assumpties!$C$24 -> 0 | D20: EUR | E20: Berekend
B21: ROI van het programma | C21: =IF(C17=0,0,C20/C17) -> 0 | D21: x | E21: Berekend (uplift / kosten)
A23: Aanbeveling
B24: 1. Start klein: 1 credit per submission, max 1/30dgn per user — voorkomt feedback-spam.
B25: 2. Closed-loop is verplicht: laat zien wat met feedback gebeurde (changelog-link in app).
B26: 3. Bouw een 'Beta Council' uit top-10 feedback-gevers: free Studio voor 6 mnd in ruil voor 1 video-call/mnd. Levert kwalitatieve insights zonder geld uit te geven.
B27: 4. Bij €5k MRR: upgrade naar gift-cards / Spotify Premium / Pioneer-DJ kortingen via partnership (advocaten worden ambassadeurs).
B28: 5. Vermijd cash-rewards onder €5k MRR — fiscaal gedoe + signaleert dat je beloning belangrijker vindt dan de feedback zelf.
